anchore/__init__.py
anchore/analyzer.py
anchore/anchore_auth.py
anchore/anchore_feeds.py
anchore/anchore_image.py
anchore/anchore_policy.py
anchore/anchore_utils.py
anchore/configuration.py
anchore/controller.py
anchore/navigator.py
anchore/version.py
anchore/anchore-modules/analyzers/01_analyzer_meta.py
anchore/anchore-modules/analyzers/02_layers.py
anchore/anchore-modules/analyzers/10_package_list.py
anchore/anchore-modules/analyzers/11_package_detail_list.py
anchore/anchore-modules/analyzers/12_gem_package_list.py
anchore/anchore-modules/analyzers/12_npm_package_list.py
anchore/anchore-modules/analyzers/13_content_search.py
anchore/anchore-modules/analyzers/13_retrieve_files.py
anchore/anchore-modules/analyzers/13_secret_search.py
anchore/anchore-modules/analyzers/20_file_list.py
anchore/anchore-modules/analyzers/30_file_checksums.py
anchore/anchore-modules/analyzers/31_file_package_verify.py
anchore/anchore-modules/analyzers/32_java_packages.py
anchore/anchore-modules/analyzers/32_python_packages.py
anchore/anchore-modules/analyzers/40_file_suids.py
anchore/anchore-modules/examples/analyzers/analyzer-example.sh
anchore/anchore-modules/examples/analyzers/analyzer-template.py
anchore/anchore-modules/examples/gates/gate-example.sh
anchore/anchore-modules/examples/gates/gate-template.py
anchore/anchore-modules/examples/multi-queries/multi-query-example.sh
anchore/anchore-modules/examples/multi-queries/multi-query-template.py
anchore/anchore-modules/examples/queries/query-example.py
anchore/anchore-modules/examples/queries/query-example.sh
anchore/anchore-modules/examples/queries/query-template.py
anchore/anchore-modules/gates/10_check_dockerfile.py
anchore/anchore-modules/gates/11_check_image.py
anchore/anchore-modules/gates/13_file_content_check.py
anchore/anchore-modules/gates/13_secret_check.py
anchore/anchore-modules/gates/20_check_package_info.py
anchore/anchore-modules/gates/20_check_pkgs.py
anchore-1.1.7.dist-info/DESCRIPTION.rst
anchore-1.1.7.dist-info/METADATA
anchore-1.1.7.dist-info/RECORD
anchore-1.1.7.dist-info/WHEEL
anchore-1.1.7.dist-info/entry_points.txt
anchore-1.1.7.dist-info/metadata.json
anchore-1.1.7.dist-info/top_level.txt
