Metadata-Version: 2.0
Name: anchore
Version: 1.1.7
Summary: A toolset for inspecting, querying, and curating containers
Home-page: https://github.com/anchore/anchore.git
Author: Anchore Inc.
Author-email: dev@anchore.com
License: Apache License 2.0
Platform: UNKNOWN
Requires-Dist: docker-py
Requires-Dist: prettytable
Requires-Dist: click
Requires-Dist: requests
Requires-Dist: pyyaml
Requires-Dist: clint
Requires-Dist: jsonschema
